pywxdump_mini/__init__.py
pywxdump_mini/simplify_wx_info.py
pywxdump_mini-2.4.2.dist-info/LICENSE
pywxdump_mini-2.4.2.dist-info/METADATA
pywxdump_mini-2.4.2.dist-info/WHEEL
pywxdump_mini-2.4.2.dist-info/entry_points.txt
pywxdump_mini-2.4.2.dist-info/top_level.txt
pywxdump_mini-2.4.2.dist-info/RECORD
