Metadata-Version: 2.1
Name: pywxdump_mini
Version: 2.4.2
Summary: 微信信息获取工具
Home-page: https://github.com/xaoyaoo/PyWxDumpMini
Author: xaoyaoo
Author-email: xaoyaoo@gmail.com
License: MIT
Classifier: Programming Language :: Python :: 3
Classifier: Operating System :: OS Independent
Requires-Python: >=3.6, <4
License-File: LICENSE
Requires-Dist: pymem
Requires-Dist: psutil
